wbltoolbox/__init__.py
wbltoolbox/common.py
wbltoolbox/spider.py
wbl-0.0.1.dist-info/LICENSE
wbl-0.0.1.dist-info/METADATA
wbl-0.0.1.dist-info/WHEEL
wbl-0.0.1.dist-info/top_level.txt
wbl-0.0.1.dist-info/RECORD
