Metadata-Version: 2.1
Name: wbl
Version: 0.0.1
Summary: some useful modules
Home-page: UNKNOWN
Author: Baolong Wang
Author-email: wangbaolong36@gmail.com
License: UNKNOWN
Platform: UNKNOWN
Classifier: Programming Language :: Python :: 3
Classifier: License :: OSI Approved :: MIT License
Classifier: Operating System :: OS Independent
Requires-Python: >=3.0
